openconnect_sso/__init__.py
openconnect_sso/app.py
openconnect_sso/authenticator.py
openconnect_sso/browser/__init__.py
openconnect_sso/browser/browser.py
openconnect_sso/browser/user.js
openconnect_sso/browser/webengine_process.py
openconnect_sso/cli.py
openconnect_sso/config.py
openconnect_sso/profile.py
openconnect_sso/saml_authenticator.py
openconnect_sso/version.py
openconnect_sso-0.8.1.dist-info/LICENSE
openconnect_sso-0.8.1.dist-info/METADATA
openconnect_sso-0.8.1.dist-info/WHEEL
openconnect_sso-0.8.1.dist-info/entry_points.txt
openconnect_sso-0.8.1.dist-info/RECORD
