Metadata-Version: 2.1
Name: openconnect-sso
Version: 0.8.1
Summary: Wrapper script for OpenConnect supporting Azure AD (SAMLv2) authentication to Cisco SSL-VPNs
Home-page: https://github.com/vlaci/openconnect-sso
License: GPL-3.0-only
Author: László Vaskó
Author-email: laszlo.vasko@outlook.com
Requires-Python: >=3.8,<4.0
Classifier: Development Status :: 4 - Beta
Classifier: Environment :: X11 Applications :: Qt
Classifier: License :: OSI Approved :: GNU General Public License v3 (GPLv3)
Classifier: Operating System :: POSIX :: Linux
Classifier: Programming Language :: Python :: 3
Classifier: Programming Language :: Python :: 3.8
Classifier: Programming Language :: Python :: 3.9
Classifier: Programming Language :: Python :: 3.10
Classifier: Programming Language :: Python :: 3.11
Classifier: Topic :: System :: Networking
Requires-Dist: PyQt6 (>=6.3.0,<7.0.0)
Requires-Dist: PyQt6-WebEngine (>=6.3.0,<7.0.0)
Requires-Dist: PySocks (>=1.7.1,<2.0.0)
Requires-Dist: attrs (>=18.2)
Requires-Dist: colorama (>=0.4,<0.5)
Requires-Dist: importlib-metadata (>=3.10.0,<4.0.0) ; python_version < "3.8"
Requires-Dist: keyring (>=21.1,<24.0.0)
Requires-Dist: lxml (>=4.3,<5.0)
Requires-Dist: prompt-toolkit (>=3.0.3,<4.0.0)
Requires-Dist: pyotp (>=2.7.0,<3.0.0)
Requires-Dist: pyxdg (>=0.26,<0.29)
Requires-Dist: requests (>=2.22,<3.0)
Requires-Dist: setuptools (>40.0)
Requires-Dist: structlog (>=20.1)
Requires-Dist: toml (>=0.10,<0.11)
Project-URL: Repository, https://github.com/vlaci/openconnect-sso
